LICENSE
MANIFEST.in
Makefile
README
setup.py
data/sleipnir.desktop
data/sleipnir.desktop.in
data/sleipnir.png
data/po/LINGUAS
data/po/Makefile
data/po/POTFILES.in
data/po/README
data/po/summary.py
data/po/validate.sh
data/ui/qml/common/README
data/ui/qml/common/common.qmlproject
data/ui/qml/common/dashboard.qml
data/ui/qml/common/window.qml
src/sleipnir/__init__.py
src/sleipnir.frontends.handset.egg-info/PKG-INFO
src/sleipnir.frontends.handset.egg-info/SOURCES.txt
src/sleipnir.frontends.handset.egg-info/dependency_links.txt
src/sleipnir.frontends.handset.egg-info/entry_points.txt
src/sleipnir.frontends.handset.egg-info/namespace_packages.txt
src/sleipnir.frontends.handset.egg-info/not-zip-safe
src/sleipnir.frontends.handset.egg-info/requires.txt
src/sleipnir.frontends.handset.egg-info/top_level.txt
src/sleipnir/frontends/__init__.py
src/sleipnir/frontends/handset/__init__.py
src/sleipnir/frontends/handset/application.py
src/sleipnir/frontends/handset/component.py
src/sleipnir/frontends/handset/constants.py
src/sleipnir/frontends/handset/controller.py
src/sleipnir/frontends/handset/helpers.py
src/sleipnir/frontends/handset/lrpc.py
src/sleipnir/frontends/handset/presenters.py
src/sleipnir/frontends/handset/profiles.py
src/sleipnir/frontends/handset/shell.py
src/sleipnir/frontends/handset/signals.py
src/sleipnir/frontends/handset/view.py
src/sleipnir/frontends/handset/windows.py
src/sleipnir/frontends/handset/flows/__init__.py
src/sleipnir/frontends/handset/flows/clients.py
src/sleipnir/frontends/handset/interfaces/__init__.py
src/sleipnir/frontends/handset/interfaces/view.py
src/sleipnir/frontends/handset/views/__init__.py
src/sleipnir/frontends/handset/views/dashboard.py
tests/__init__.py
tests/integration/__init__.py